rundeck_executions_cleanup/__init__.py
rundeck_executions_cleanup/__main__.py
rundeck_executions_cleanup/rundeck_api.py
rundeck_executions_cleanup-0.1.3.dist-info/entry_points.txt
rundeck_executions_cleanup-0.1.3.dist-info/WHEEL
rundeck_executions_cleanup-0.1.3.dist-info/METADATA
rundeck_executions_cleanup-0.1.3.dist-info/RECORD
